MDIO_tester.v
`timescale 1ns/1ps

module tester (
    output reg clk,
    output reg reset,
    output reg MDIO_START,
    output reg MDIO_IN,
    output reg [31:0] T_DATA,
    input MDC,
    input MDIO_OUT,
    input MDIO_OE,
    input [15:0] RD_DATA,
    input DATA_RDY,
    input [4:0] counter
);

always begin
    #5 clk = !clk;  
end

initial begin
    clk = 0;
    reset = 0;
    T_DATA = 0;
    MDIO_START =0;

end
initial begin
    #10
    reset =1;
    T_DATA = 32'hAAAAAAAA;
    #10 
    MDIO_START = 1;
    #10
    // MDIO_START = 0;
    //wait(DATA_RDY)
    #400
    $finish;  
end

endmodule

MDIO.v
/*
Estudiante: David Lucas Martínez
Carnet: B74333
Estudiante: Kevin Jimenez Acuna
Carnet: C13876
Evualuacion: Proyecto

Archivo: MDIO.v

*/
module MDIO (
    input clk,
    input reset,
    input MDIO_START,
    input MDIO_IN,
    input [31:0] T_DATA,
    output reg MDC,
    output reg MDIO_OUT,
    output reg MDIO_OE,
    output reg [15:0] RD_DATA,
    output reg DATA_RDY,
    output [5:0] counter
);

reg [6:0] count;

always @(posedge clk) begin
    if(!reset) begin
        MDC <= 0;
        MDIO_OUT <= 0;
        MDIO_OE <= 0;
        RD_DATA <= 0;
        DATA_RDY <= 0;
        count <= 6'd32;
    end
    else begin 
        if (MDIO_START) begin
            if(count > 0) begin
                MDIO_OUT <= T_DATA[count-1]; 
                count <= count -1;
            end else begin
                DATA_RDY <= 1;
                MDIO_OE <= 0;
            end
        end
    end
    
end

assign counter = count;

endmodule

MDIO_testbench.v
`include "MDIO.v"
`include "MDIO_tester.v"

module testebench;
    
    wire clk, reset, MDIO_START, MDIO_IN, MDC, MDIO_OUT, MDIO_OE, DATA_RDY;
    wire [15:0] RD_DATA;
    wire [31:0] T_DATA;
    wire [5:0]  counter;
    

    MDIO DUT(
        .clk(clk),
        .reset(reset),
        .MDIO_START(MDIO_START),
        .MDIO_IN(MDIO_IN),
        .T_DATA(T_DATA[31:0]),
        .counter(counter[5:0]),
        .MDC(MDC),
        .MDIO_OUT(MDIO_OUT),
        .MDIO_OE(MDIO_OE),
        .RD_DATA(RD_DATA[15:0]),
        .DATA_RDY(DATA_RDY)
    );

    tester TESTER(
        .clk(clk),
        .reset(reset),
        .MDIO_START(MDIO_START),
        .MDIO_IN(MDIO_IN),
        .T_DATA(T_DATA[31:0]),
        .counter(counter[5:0]),
        .MDC(MDC),
        .MDIO_OUT(MDIO_OUT),
        .MDIO_OE(MDIO_OE),
        .RD_DATA(RD_DATA[15:0]),
        .DATA_RDY(DATA_RDY)
    );

    initial begin
        $dumpfile("tb.vcd");
        $dumpvars;
    end
    
endmodule

tb.vcd
$date
	Mon Jun 17 00:28:37 2024
$end
$version
	Icarus Verilog
$end
$timescale
	1ps
$end
$scope module testebench $end
$var wire 1 ! reset $end
$var wire 6 " counter [5:0] $end
$var wire 1 # clk $end
$var wire 32 $ T_DATA [31:0] $end
$var wire 16 % RD_DATA [15:0] $end
$var wire 1 & MDIO_START $end
$var wire 1 ' MDIO_OUT $end
$var wire 1 ( MDIO_OE $end
$var wire 1 ) MDIO_IN $end
$var wire 1 * MDC $end
$var wire 1 + DATA_RDY $end
$scope module DUT $end
$var wire 1 ! reset $end
$var wire 6 , counter [5:0] $end
$var wire 1 # clk $end
$var wire 32 - T_DATA [31:0] $end
$var wire 1 & MDIO_START $end
$var wire 1 ) MDIO_IN $end
$var reg 1 + DATA_RDY $end
$var reg 1 * MDC $end
$var reg 1 ( MDIO_OE $end
$var reg 1 ' MDIO_OUT $end
$var reg 16 . RD_DATA [15:0] $end
$var reg 7 / count [6:0] $end
$upscope $end
$scope module TESTER $end
$var wire 1 + DATA_RDY $end
$var wire 1 * MDC $end
$var wire 1 ( MDIO_OE $end
$var wire 1 ' MDIO_OUT $end
$var wire 16 0 RD_DATA [15:0] $end
$var wire 5 1 counter [4:0] $end
$var reg 1 ) MDIO_IN $end
$var reg 1 & MDIO_START $end
$var reg 32 2 T_DATA [31:0] $end
$var reg 1 # clk $end
$var reg 1 ! reset $end
$upscope $end
$upscope $end
$enddefinitions $end
#0
$dumpvars
b0 2
bx 1
bx 0
bx /
bx .
b0 -
bx ,
x+
x*
x)
x(
x'
0&
bx %
b0 $
0#
bx "
0!
$end
#5000
b0 1
b100000 "
b100000 ,
b100000 /
0+
b0 %
b0 .
b0 0
0(
0'
0*
1#
#10000
0#
b10101010101010101010101010101010 $
b10101010101010101010101010101010 -
b10101010101010101010101010101010 2
1!
#15000
1#
#20000
0#
1&
#25000
b11111 1
b11111 "
b11111 ,
b11111 /
1'
1#
#30000
0#
#35000
b11110 1
b11110 "
b11110 ,
b11110 /
0'
1#
#40000
0#
#45000
b11101 1
b11101 "
b11101 ,
b11101 /
1'
1#
#50000
0#
#55000
b11100 1
b11100 "
b11100 ,
b11100 /
0'
1#
#60000
0#
#65000
b11011 1
b11011 "
b11011 ,
b11011 /
1'
1#
#70000
0#
#75000
b11010 1
b11010 "
b11010 ,
b11010 /
0'
1#
#80000
0#
#85000
b11001 1
b11001 "
b11001 ,
b11001 /
1'
1#
#90000
0#
#95000
b11000 1
b11000 "
b11000 ,
b11000 /
0'
1#
#100000
0#
#105000
b10111 1
b10111 "
b10111 ,
b10111 /
1'
1#
#110000
0#
#115000
b10110 1
b10110 "
b10110 ,
b10110 /
0'
1#
#120000
0#
#125000
b10101 1
b10101 "
b10101 ,
b10101 /
1'
1#
#130000
0#
#135000
b10100 1
b10100 "
b10100 ,
b10100 /
0'
1#
#140000
0#
#145000
b10011 1
b10011 "
b10011 ,
b10011 /
1'
1#
#150000
0#
#155000
b10010 1
b10010 "
b10010 ,
b10010 /
0'
1#
#160000
0#
#165000
b10001 1
b10001 "
b10001 ,
b10001 /
1'
1#
#170000
0#
#175000
b10000 1
b10000 "
b10000 ,
b10000 /
0'
1#
#180000
0#
#185000
b1111 1
b1111 "
b1111 ,
b1111 /
1'
1#
#190000
0#
#195000
b1110 1
b1110 "
b1110 ,
b1110 /
0'
1#
#200000
0#
#205000
b1101 1
b1101 "
b1101 ,
b1101 /
1'
1#
#210000
0#
#215000
b1100 1
b1100 "
b1100 ,
b1100 /
0'
1#
#220000
0#
#225000
b1011 1
b1011 "
b1011 ,
b1011 /
1'
1#
#230000
0#
#235000
b1010 1
b1010 "
b1010 ,
b1010 /
0'
1#
#240000
0#
#245000
b1001 1
b1001 "
b1001 ,
b1001 /
1'
1#
#250000
0#
#255000
b1000 1
b1000 "
b1000 ,
b1000 /
0'
1#
#260000
0#
#265000
b111 1
b111 "
b111 ,
b111 /
1'
1#
#270000
0#
#275000
b110 1
b110 "
b110 ,
b110 /
0'
1#
#280000
0#
#285000
b101 1
b101 "
b101 ,
b101 /
1'
1#
#290000
0#
#295000
b100 1
b100 "
b100 ,
b100 /
0'
1#
#300000
0#
#305000
b11 1
b11 "
b11 ,
b11 /
1'
1#
#310000
0#
#315000
b10 1
b10 "
b10 ,
b10 /
0'
1#
#320000
0#
#325000
b1 1
b1 "
b1 ,
b1 /
1'
1#
#330000
0#
#335000
b0 1
b0 "
b0 ,
b0 /
0'
1#
#340000
0#
#345000
1+
1#
