MDIO_tester.v
`timescale 1ns/1ps

module tester (
    output reg clk,
    output reg reset,
    output reg MDIO_START,
    output reg MDIO_IN,
    output reg [31:0] T_DATA,
    input MDC,
    input MDIO_OUT,
    input MDIO_OE,
    input [15:0] RD_DATA,
    input DATA_RDY,
    input [5:0] counter
);

always begin
    #5 clk = !clk;  
end

initial begin
    clk = 0;
    reset = 0;
    T_DATA = 0;
    MDIO_START =0;

end
initial begin
    //Caso de Escritura
    #10
    reset =1;
    T_DATA = 32'h8C6AF5B5; 
    #10 
    MDIO_START = 1;
    #10
    MDIO_START = 0;
    #400
    $finish;  
end

endmodule

MDIO.v
/*
Estudiante: David Lucas Martínez
Carnet: B74333
Estudiante: Kevin Jimenez Acuna
Carnet: C13876
Evualuacion: Proyecto

Archivo: MDIO.v

*/
module MDIO (
    input clk,
    input reset,
    input MDIO_START,
    input MDIO_IN,
    input [31:0] T_DATA,
    output reg MDC,
    output reg MDIO_OUT,
    output reg MDIO_OE,
    output reg [15:0] RD_DATA,
    output reg DATA_RDY,
    output [5:0] counter
);

reg [5:0] count;
reg mdio_start_d; 
reg [1:0] state;




always @(posedge clk) begin
    if(!reset) begin
        MDC <= 0;
        MDIO_OUT <= 0;
        MDIO_OE <= 0;
        RD_DATA <= 0;
        DATA_RDY <= 0;
        count <= 6'd32;
        mdio_start_d <=0;
    end
    else begin 
        
        MDC <= ~MDC;//cada posedge se cambia el estado de MDC para dividir a la mitad la frecuencia
        if(MDIO_START) begin
            mdio_start_d <= MDIO_START;//Señal complementaría para poder usarla para iniciar la transmisión
        end
        
        if(mdio_start_d) begin
            MDIO_OE <= 1;// Si mdio_start_1 significa que hay una escritura por lo que se pone en uno
            if(count > 0) begin
                MDIO_OUT <= T_DATA[count-1]; 
                count <= count -1;
            end else begin
                mdio_start_d = 0;
                MDIO_OE <= 0; //Se pone en 0 cuando terminan los 32 ciclos
                count <= 6'd32; //Se reincia el contador
            end
        end else begin 
            MDIO_OE <= 1;
            if(count > 0) begin
                if(count < 16) begin //cuando sea menor a 16 se baja
                    MDIO_OE <= 0;
                    RD_DATA <= {RD_DATA[14:0], MDIO_IN}; //Se concatena el bit de MDIO_IN a los 15 bits menos significativos, 
                    count <= count -1; //y asi generar 16 bits, y se repite hasta haber creado la palabra de 16 bits
                end
            end else begin
                DATA_RDY <= 1;
            end
            
        end
    end
    
end

assign counter = count;

endmodule

MDIO_testbench.v
`include "MDIO.v"
`include "MDIO_tester.v"

module testebench;
    
    wire clk, reset, MDIO_START, MDIO_IN, MDC, MDIO_OUT, MDIO_OE, DATA_RDY;
    wire [15:0] RD_DATA;
    wire [31:0] T_DATA;
    wire [5:0]  counter;
    

    MDIO DUT(
        .clk(clk),
        .reset(reset),
        .MDIO_START(MDIO_START),
        .MDIO_IN(MDIO_IN),
        .T_DATA(T_DATA[31:0]),
        .counter(counter[5:0]),
        .MDC(MDC),
        .MDIO_OUT(MDIO_OUT),
        .MDIO_OE(MDIO_OE),
        .RD_DATA(RD_DATA[15:0]),
        .DATA_RDY(DATA_RDY)
    );

    tester TESTER(
        .clk(clk),
        .reset(reset),
        .MDIO_START(MDIO_START),
        .MDIO_IN(MDIO_IN),
        .T_DATA(T_DATA[31:0]),
        .counter(counter[5:0]),
        .MDC(MDC),
        .MDIO_OUT(MDIO_OUT),
        .MDIO_OE(MDIO_OE),
        .RD_DATA(RD_DATA[15:0]),
        .DATA_RDY(DATA_RDY)
    );

    initial begin
        $dumpfile("tb.vcd");
        $dumpvars;
    end
    
endmodule

tb.vcd
$date
	Tue Jun 18 21:58:10 2024
$end
$version
	Icarus Verilog
$end
$timescale
	1ps
$end
$scope module testebench $end
$var wire 1 ! reset $end
$var wire 6 " counter [5:0] $end
$var wire 1 # clk $end
$var wire 32 $ T_DATA [31:0] $end
$var wire 16 % RD_DATA [15:0] $end
$var wire 1 & MDIO_START $end
$var wire 1 ' MDIO_OUT $end
$var wire 1 ( MDIO_OE $end
$var wire 1 ) MDIO_IN $end
$var wire 1 * MDC $end
$var wire 1 + DATA_RDY $end
$scope module DUT $end
$var wire 6 , counter [5:0] $end
$var wire 1 ! reset $end
$var wire 1 # clk $end
$var wire 32 - T_DATA [31:0] $end
$var wire 1 & MDIO_START $end
$var wire 1 ) MDIO_IN $end
$var reg 1 + DATA_RDY $end
$var reg 1 * MDC $end
$var reg 1 ( MDIO_OE $end
$var reg 1 ' MDIO_OUT $end
$var reg 16 . RD_DATA [15:0] $end
$var reg 6 / count [5:0] $end
$var reg 1 0 mdio_start_d $end
$upscope $end
$scope module TESTER $end
$var wire 1 + DATA_RDY $end
$var wire 1 * MDC $end
$var wire 1 ( MDIO_OE $end
$var wire 1 ' MDIO_OUT $end
$var wire 16 1 RD_DATA [15:0] $end
$var wire 6 2 counter [5:0] $end
$var reg 1 ) MDIO_IN $end
$var reg 1 & MDIO_START $end
$var reg 32 3 T_DATA [31:0] $end
$var reg 1 # clk $end
$var reg 1 ! reset $end
$upscope $end
$upscope $end
$enddefinitions $end
#0
$dumpvars
b0 3
bx 2
bx 1
x0
bx /
bx .
b0 -
bx ,
x+
x*
x)
x(
x'
0&
bx %
b0 $
0#
bx "
0!
$end
#5000
00
b100000 "
b100000 ,
b100000 2
b100000 /
0+
b0 %
b0 .
b0 1
0(
0'
0*
1#
#10000
0#
b10001100011010101111010110110101 $
b10001100011010101111010110110101 -
b10001100011010101111010110110101 3
1!
#15000
1(
1*
1#
#20000
0#
1&
#25000
10
0*
1#
#30000
0#
0&
#35000
b11111 "
b11111 ,
b11111 2
b11111 /
1'
1*
1#
#40000
0#
#45000
b11110 "
b11110 ,
b11110 2
b11110 /
0'
0*
1#
#50000
0#
#55000
b11101 "
b11101 ,
b11101 2
b11101 /
1*
1#
#60000
0#
#65000
b11100 "
b11100 ,
b11100 2
b11100 /
0*
1#
#70000
0#
#75000
b11011 "
b11011 ,
b11011 2
b11011 /
1'
1*
1#
#80000
0#
#85000
b11010 "
b11010 ,
b11010 2
b11010 /
0*
1#
#90000
0#
#95000
b11001 "
b11001 ,
b11001 2
b11001 /
0'
1*
1#
#100000
0#
#105000
b11000 "
b11000 ,
b11000 2
b11000 /
0*
1#
#110000
0#
#115000
b10111 "
b10111 ,
b10111 2
b10111 /
1*
1#
#120000
0#
#125000
b10110 "
b10110 ,
b10110 2
b10110 /
1'
0*
1#
#130000
0#
#135000
b10101 "
b10101 ,
b10101 2
b10101 /
1*
1#
#140000
0#
#145000
b10100 "
b10100 ,
b10100 2
b10100 /
0'
0*
1#
#150000
0#
#155000
b10011 "
b10011 ,
b10011 2
b10011 /
1'
1*
1#
#160000
0#
#165000
b10010 "
b10010 ,
b10010 2
b10010 /
0'
0*
1#
#170000
0#
#175000
b10001 "
b10001 ,
b10001 2
b10001 /
1'
1*
1#
#180000
0#
#185000
b10000 "
b10000 ,
b10000 2
b10000 /
0'
0*
1#
#190000
0#
#195000
b1111 "
b1111 ,
b1111 2
b1111 /
1'
1*
1#
#200000
0#
#205000
b1110 "
b1110 ,
b1110 2
b1110 /
0*
1#
#210000
0#
#215000
b1101 "
b1101 ,
b1101 2
b1101 /
1*
1#
#220000
0#
#225000
b1100 "
b1100 ,
b1100 2
b1100 /
0*
1#
#230000
0#
#235000
b1011 "
b1011 ,
b1011 2
b1011 /
0'
1*
1#
#240000
0#
#245000
b1010 "
b1010 ,
b1010 2
b1010 /
1'
0*
1#
#250000
0#
#255000
b1001 "
b1001 ,
b1001 2
b1001 /
0'
1*
1#
#260000
0#
#265000
b1000 "
b1000 ,
b1000 2
b1000 /
1'
0*
1#
#270000
0#
#275000
b111 "
b111 ,
b111 2
b111 /
1*
1#
#280000
0#
#285000
b110 "
b110 ,
b110 2
b110 /
0'
0*
1#
#290000
0#
#295000
b101 "
b101 ,
b101 2
b101 /
1'
1*
1#
#300000
0#
#305000
b100 "
b100 ,
b100 2
b100 /
0*
1#
#310000
0#
#315000
b11 "
b11 ,
b11 2
b11 /
0'
1*
1#
#320000
0#
#325000
b10 "
b10 ,
b10 2
b10 /
1'
0*
1#
#330000
0#
#335000
b1 "
b1 ,
b1 2
b1 /
0'
1*
1#
#340000
0#
#345000
b0 "
b0 ,
b0 2
b0 /
1'
0*
1#
#350000
0#
#355000
b100000 "
b100000 ,
b100000 2
b100000 /
0(
1*
00
1#
#360000
0#
#365000
1(
0*
1#
#370000
0#
#375000
1*
1#
#380000
0#
#385000
0*
1#
#390000
0#
#395000
1*
1#
#400000
0#
#405000
0*
1#
#410000
0#
#415000
1*
1#
#420000
0#
#425000
0*
1#
